Metadata-Version: 2.1
Name: dtnt4mailsender
Version: 1.0
Summary: Module to send email with file
Author: DevTools_and_Tier-4
Author-email: DevTools_and_Tier_4@outlook.com
